{"paths":{"0":["bg",0],"1":["TiledMap/test_infinite/test_infinite",0],"2":["bg",1,1],"3":["level/levelAtlas",3],"4":["level/v1/海鸥1",1,1],"5":["level/v1/海鸥2",1,1],"6":["level/v1/海鸥3",1,1],"7":["level/v1/海鸥4",1,1],"8":["level/v2/0",1,1],"9":["level/v2/1",1,1],"10":["level/v2/10",1,1],"11":["level/v2/11",1,1],"12":["level/v2/12",1,1],"13":["level/v2/13",1,1],"14":["level/v2/14",1,1],"15":["level/v2/15",1,1],"16":["level/v2/16",1,1],"17":["level/v2/17",1,1],"18":["level/v2/18",1,1],"19":["level/v2/19",1,1],"20":["level/v2/2",1,1],"21":["level/v2/20",1,1],"22":["level/v2/21",1,1],"23":["level/v2/22",1,1],"24":["level/v2/23",1,1],"25":["level/v2/24",1,1],"26":["level/v2/25",1,1],"27":["level/v2/26",1,1],"28":["level/v2/27",1,1],"29":["level/v2/28",1,1],"30":["level/v2/29",1,1],"31":["level/v2/3",1,1],"32":["level/v2/4",1,1],"33":["level/v2/5",1,1],"34":["level/v2/6",1,1],"35":["level/v2/7",1,1],"36":["level/v2/8",1,1],"37":["level/v2/9",1,1],"38":["TiledMap/test_infinite/test_infinite",1,1],"39":["TiledMap/test_infinite/test_infinite",2]},"types":["cc.Texture2D","cc.SpriteFrame","cc.TiledMapAsset","cc.SpriteAtlas"],"uuids":["0e7Wm11FhPPaujv0mPK63w","58ck4QujZDTqrpwKqdmZfO","faJJ6ShYpGVrMrjms/zcs8","73m34Mf6RA2ICahtzV9aGR","1fgB3X+P5NP49wPjhNLVgT","daQHnVpKFASb42sQaqLd+9","a1CB/QNitG46bZAhINDv1f","72XoNW935GFpr2uIbNFmxk","c5OPe+wEJHn6Bt7ui3PdIU","a9HJ+fb/RLsYCfFXe98msd","b88TKzTKpJnKwYP8oT7LKt","0a7vaIzudAVLOmogOvIk/v","f8RVlKPhZHsKr5FFQfyFrE","1bNGoQxutPpa2tW+FGSLN0","cbN2b01qtACb1ZHCn0fNPl","70+Pl4wFJJ+L/oPt9khLKN","04OfQ5HctHhK4VljZMvsRD","8c7h1P2W1G2YdgB6yNN1Xs","2bNxkthIBIJajK3XwTRHMr","d0ZzU4ROtGPbuzwnl/gwLW","d8ynQN7npMR79e99bi1vSo","24+7RUIipPNoK9XvZ3Zopx","66czdNBalE+bQ0jKiSyWaR","f6m2WAPQlMo6eaUQNEKgeJ","4cJKcSQhRBY7YOw4egBC7A","90+ExABDJDQ7EhPA9rn/S+","7fDVQ4B/lHSI0OdeHTXLjs","0aI1CN+X9BP5Ek4MwL8QXH","f450sOEfJFuKEOyU86p2ZS","d9y5bwyDFC5oIhMpsbR2U9","c60DKJZKxIPpq777sI/iTF","bb+k4H1lZELqEf/vRXMLfW","3ctRVUgnxPq4LWHZKfq+yp","9ezU0JYJtKIpExcj3s9xFJ","c99YcJTXBFwbcgsVW3yg54","98FsVVk/BImZtkU3h1JOlp","2aBRam+2pPYagYAHDQKHKH","aba6TaSWVHB44WQv9nFD+t","f0QNwT/cdMna0w9qYxIfz6","a4yLsqgXxGLLs/cSmySfi8","16858ed28"],"scenes":{},"redirect":[],"deps":[],"packs":{"0e647c65d":[0,40,1]},"name":"resources","importBase":"import","nativeBase":"native","debug":false,"isZip":false,"encrypted":false,"versions":{"import":[16,"c205c",27,"9313f",11,"bfc6a","0e647c65d","68c51",13,"652b2",4,"d147f",21,"98223",36,"1881c",18,"069c7",32,"0de7b",24,"9dbb9",22,"c9421",15,"84570",7,"6a4cd",3,"a60a8",26,"0e40c",17,"7efa2",25,"53b1f",35,"dfe3e",33,"b1370",6,"832f6",39,"56d5c",9,"d156f",37,"00ed9",10,"b321d",31,"7e6ca",8,"b3177",30,"fe19c",34,"44412",14,"2149d",19,"e9cd9",20,"ecdd6",29,"2c551",5,"d8eef",38,"1033d",28,"d8185",23,"044d2",12,"fbc1d",2,"16389"],"native":[0,"1774a",40,"8f72e",1,"7bbd4"]}}